MANIFEST.in
setup.py
riemann_runit/__init__.py
riemann_runit/main.py
riemann_runit/version.py
riemann_runit.egg-info/PKG-INFO
riemann_runit.egg-info/SOURCES.txt
riemann_runit.egg-info/dependency_links.txt
riemann_runit.egg-info/entry_points.txt
riemann_runit.egg-info/requires.txt
riemann_runit.egg-info/top_level.txt