Metadata-Version: 1.1
Name: riemann-runit
Version: 0.3
Summary: Riemann runit collector
Home-page: https://github.com/kensho/riemann-runit
Author: Ashok Rao
Author-email: ops@kensho.com
License: MIT
Platform: UNKNOWN
Classifier: Development Status :: 4 - Beta
Classifier: Intended Audience :: Developers
Classifier: License :: OSI Approved :: MIT License
Classifier: Natural Language :: English
Classifier: Operating System :: Unix
Classifier: Programming Language :: Python :: 2.7
Classifier: Operating System :: OS Independent
